{
  "id": "rithysak",
  "realm": "rithysak",
  "notBefore": 0,
  "defaultSignatureAlgorithm": "RS256",
  "revokeRefreshToken": false,
  "refreshTokenMaxReuse": 0,
  "accessTokenLifespan": 300,
  "accessTokenLifespanForImplicitFlow": 900,
  "ssoSessionIdleTimeout": 1800,
  "ssoSessionMaxLifespan": 36000,
  "ssoSessionIdleTimeoutRememberMe": 0,
  "ssoSessionMaxLifespanRememberMe": 0,
  "offlineSessionIdleTimeout": 2592000,
  "offlineSessionMaxLifespanEnabled": false,
  "offlineSessionMaxLifespan": 5184000,
  "clientSessionIdleTimeout": 0,
  "clientSessionMaxLifespan": 0,
  "clientOfflineSessionIdleTimeout": 0,
  "clientOfflineSessionMaxLifespan": 0,
  "accessCodeLifespan": 60,
  "accessCodeLifespanUserAction": 300,
  "accessCodeLifespanLogin": 1800,
  "actionTokenGeneratedByAdminLifespan": 43200,
  "actionTokenGeneratedByUserLifespan": 300,
  "oauth2DeviceCodeLifespan": 600,
  "oauth2DevicePollingInterval": 5,
  "enabled": true,
  "sslRequired": "external",
  "registrationAllowed": false,
  "registrationEmailAsUsername": false,
  "rememberMe": false,
  "verifyEmail": false,
  "loginWithEmailAllowed": true,
  "duplicateEmailsAllowed": false,
  "resetPasswordAllowed": false,
  "editUsernameAllowed": false,
  "bruteForceProtected": false,
  "permanentLockout": false,
  "maxFailureWaitSeconds": 900,
  "minimumQuickLoginWaitSeconds": 60,
  "waitIncrementSeconds": 60,
  "quickLoginCheckMilliSeconds": 1000,
  "maxDeltaTimeSeconds": 43200,
  "failureFactor": 30,
  "roles": {
    "realm": [
      {
        "id": "3d1b527d-88a7-49d7-b096-5faa6da0c0fa",
        "name": "uma_authorization",
        "description": "${role_uma_authorization}",
        "composite": false,
        "clientRole": false,
        "containerId": "rithysak",
        "attributes": {}
      },
      {
        "id": "15e3e25d-fff0-492b-bc6e-5a37c6cf42c7",
        "name": "offline_access",
        "description": "${role_offline-access}",
        "composite": false,
        "clientRole": false,
        "containerId": "rithysak",
        "attributes": {}
      },
      {
        "id": "e59d4e1c-9c5c-4747-9269-4ab307b48684",
        "name": "default-roles-rithysak",
        "description": "${role_default-roles}",
        "composite": true,
        "composites": {
          "realm": [
            "offline_access",
            "uma_authorization"
          ],
          "client": {
            "account": [
              "manage-account",
              "view-profile"
            ]
          }
        },
        "clientRole": false,
        "containerId": "rithysak",
        "attributes": {}
      }
    ],
    "client": {
      "realm-management": [
        {
          "id": "3a306cd4-520c-4269-b685-f2970fabe2b5",
          "name": "view-clients",
          "description": "${role_view-clients}",
          "composite": true,
          "composites": {
            "client": {
              "realm-management": [
                "query-clients"
              ]
            }
          },
          "clientRole": true,
          "containerId": "841a68af-d514-4e41-be8e-d1dfeae9285e",
          "attributes": {}
        },
        {
          "id": "6979a970-135d-4281-9d9e-84744a3e44e9",
          "name": "view-users",
          "description": "${role_view-users}",
          "composite": true,
          "composites": {
            "client": {
              "realm-management": [
                "query-users",
                "query-groups"
              ]
            }
          },
          "clientRole": true,
          "containerId": "841a68af-d514-4e41-be8e-d1dfeae9285e",
          "attributes": {}
        },
        {
          "id": "98f6ad7d-e08c-4a16-a456-2de2d1d94b16",
          "name": "impersonation",
          "description": "${role_impersonation}",
          "composite": false,
          "clientRole": true,
          "containerId": "841a68af-d514-4e41-be8e-d1dfeae9285e",
          "attributes": {}
        },
        {
          "id": "d28e5661-cd4a-4eb2-ab9f-840498125d26",
          "name": "view-events",
          "description": "${role_view-events}",
          "composite": false,
          "clientRole": true,
          "containerId": "841a68af-d514-4e41-be8e-d1dfeae9285e",
          "attributes": {}
        },
        {
          "id": "e4ca8dd3-7e63-43b8-8234-e68530a206bd",
          "name": "view-identity-providers",
          "description": "${role_view-identity-providers}",
          "composite": false,
          "clientRole": true,
          "containerId": "841a68af-d514-4e41-be8e-d1dfeae9285e",
          "attributes": {}
        },
        {
          "id": "a4a51ead-e362-4357-a812-6c239be481fe",
          "name": "manage-identity-providers",
          "description": "${role_manage-identity-providers}",
          "composite": false,
          "clientRole": true,
          "containerId": "841a68af-d514-4e41-be8e-d1dfeae9285e",
          "attributes": {}
        },
        {
          "id": "6a78a1ed-d2d8-44ad-be7b-500ce3b529ab",
          "name": "manage-events",
          "description": "${role_manage-events}",
          "composite": false,
          "clientRole": true,
          "containerId": "841a68af-d514-4e41-be8e-d1dfeae9285e",
          "attributes": {}
        },
        {
          "id": "846f2d1d-bc19-4b61-b34b-4e843b3bd7d0",
          "name": "view-authorization",
          "description": "${role_view-authorization}",
          "composite": false,
          "clientRole": true,
          "containerId": "841a68af-d514-4e41-be8e-d1dfeae9285e",
          "attributes": {}
        },
        {
          "id": "3c0921ca-0916-4433-907c-5116dccbbdfb",
          "name": "create-client",
          "description": "${role_create-client}",
          "composite": false,
          "clientRole": true,
          "containerId": "841a68af-d514-4e41-be8e-d1dfeae9285e",
          "attributes": {}
        },
        {
          "id": "c8ec4ccb-0b2c-44df-9dc9-a197b2b47d84",
          "name": "realm-admin",
          "description": "${role_realm-admin}",
          "composite": true,
          "composites": {
            "client": {
              "realm-management": [
                "view-users",
                "view-clients",
                "impersonation",
                "view-events",
                "view-identity-providers",
                "manage-identity-providers",
                "manage-events",
                "view-authorization",
                "create-client",
                "query-realms",
                "query-users",
                "manage-authorization",
                "manage-clients",
                "query-clients",
                "view-realm",
                "manage-realm",
                "query-groups",
                "manage-users"
              ]
            }
          },
          "clientRole": true,
          "containerId": "841a68af-d514-4e41-be8e-d1dfeae9285e",
          "attributes": {}
        },
        {
          "id": "13166521-60f1-40b4-b17e-75664fe00296",
          "name": "query-realms",
          "description": "${role_query-realms}",
          "composite": false,
          "clientRole": true,
          "containerId": "841a68af-d514-4e41-be8e-d1dfeae9285e",
          "attributes": {}
        },
        {
          "id": "10ff8a30-05ab-4690-a43c-9f93060785cc",
          "name": "query-users",
          "description": "${role_query-users}",
          "composite": false,
          "clientRole": true,
          "containerId": "841a68af-d514-4e41-be8e-d1dfeae9285e",
          "attributes": {}
        },
        {
          "id": "611ff542-8544-49f9-b1b3-ee656135846d",
          "name": "manage-authorization",
          "description": "${role_manage-authorization}",
          "composite": false,
          "clientRole": true,
          "containerId": "841a68af-d514-4e41-be8e-d1dfeae9285e",
          "attributes": {}
        },
        {
          "id": "a08a2efd-04b8-4ca4-8087-674fddd978bb",
          "name": "manage-clients",
          "description": "${role_manage-clients}",
          "composite": false,
          "clientRole": true,
          "containerId": "841a68af-d514-4e41-be8e-d1dfeae9285e",
          "attributes": {}
        },
        {
          "id": "2a9bcea0-15b5-423a-afaf-52e4abfaa7ad",
          "name": "query-clients",
          "description": "${role_query-clients}",
          "composite": false,
          "clientRole": true,
          "containerId": "841a68af-d514-4e41-be8e-d1dfeae9285e",
          "attributes": {}
        },
        {
          "id": "fed6ad25-0a2d-49df-ab53-a7fec1146ad6",
          "name": "manage-realm",
          "description": "${role_manage-realm}",
          "composite": false,
          "clientRole": true,
          "containerId": "841a68af-d514-4e41-be8e-d1dfeae9285e",
          "attributes": {}
        },
        {
          "id": "c11ac638-403f-44cf-858b-fd0a74f99fec",
          "name": "query-groups",
          "description": "${role_query-groups}",
          "composite": false,
          "clientRole": true,
          "containerId": "841a68af-d514-4e41-be8e-d1dfeae9285e",
          "attributes": {}
        },
        {
          "id": "1106f015-a461-447b-8dd4-a8a1883b1ddd",
          "name": "view-realm",
          "description": "${role_view-realm}",
          "composite": false,
          "clientRole": true,
          "containerId": "841a68af-d514-4e41-be8e-d1dfeae9285e",
          "attributes": {}
        },
        {
          "id": "39e7f680-6514-4285-8e87-79e2e1a0a0fd",
          "name": "manage-users",
          "description": "${role_manage-users}",
          "composite": false,
          "clientRole": true,
          "containerId": "841a68af-d514-4e41-be8e-d1dfeae9285e",
          "attributes": {}
        }
      ],
      "security-admin-console": [],
      "admin-cli": [],
      "account-console": [],
      "broker": [
        {
          "id": "c7221553-1654-437f-bcfc-639d45c9e975",
          "name": "read-token",
          "description": "${role_read-token}",
          "composite": false,
          "clientRole": true,
          "containerId": "c3568581-b28b-445d-b3b0-197b5d11a4f5",
          "attributes": {}
        }
      ],
      "rithysak-client": [],
      "account": [
        {
          "id": "6d6cae00-8aa5-4eca-9ef4-30d217588e4c",
          "name": "manage-account",
          "description": "${role_manage-account}",
          "composite": true,
          "composites": {
            "client": {
              "account": [
                "manage-account-links"
              ]
            }
          },
          "clientRole": true,
          "containerId": "566c3205-b080-462e-b430-c96cf518c781",
          "attributes": {}
        },
        {
          "id": "37f569a1-eee6-4513-a692-24033ab6e8c7",
          "name": "view-profile",
          "description": "${role_view-profile}",
          "composite": false,
          "clientRole": true,
          "containerId": "566c3205-b080-462e-b430-c96cf518c781",
          "attributes": {}
        },
        {
          "id": "eb95643a-9aa2-4eab-ba09-3d0133a8a575",
          "name": "manage-account-links",
          "description": "${role_manage-account-links}",
          "composite": false,
          "clientRole": true,
          "containerId": "566c3205-b080-462e-b430-c96cf518c781",
          "attributes": {}
        },
        {
          "id": "5fcccb35-e3a5-4589-a0f2-6ba6450cf8c1",
          "name": "delete-account",
          "description": "${role_delete-account}",
          "composite": false,
          "clientRole": true,
          "containerId": "566c3205-b080-462e-b430-c96cf518c781",
          "attributes": {}
        },
        {
          "id": "8331a329-5049-4613-be56-0ba0550a8ab7",
          "name": "manage-consent",
          "description": "${role_manage-consent}",
          "composite": true,
          "composites": {
            "client": {
              "account": [
                "view-consent"
              ]
            }
          },
          "clientRole": true,
          "containerId": "566c3205-b080-462e-b430-c96cf518c781",
          "attributes": {}
        },
        {
          "id": "28f4c78c-63dd-4e06-b97c-7c384ce64c76",
          "name": "view-applications",
          "description": "${role_view-applications}",
          "composite": false,
          "clientRole": true,
          "containerId": "566c3205-b080-462e-b430-c96cf518c781",
          "attributes": {}
        },
        {
          "id": "eaa03570-fbae-452e-85a0-6f84f2700e1a",
          "name": "view-consent",
          "description": "${role_view-consent}",
          "composite": false,
          "clientRole": true,
          "containerId": "566c3205-b080-462e-b430-c96cf518c781",
          "attributes": {}
        }
      ]
    }
  },
  "groups": [],
  "defaultRole": {
    "id": "e59d4e1c-9c5c-4747-9269-4ab307b48684",
    "name": "default-roles-rithysak",
    "description": "${role_default-roles}",
    "composite": true,
    "clientRole": false,
    "containerId": "rithysak"
  },
  "requiredCredentials": [
    "password"
  ],
  "otpPolicyType": "totp",
  "otpPolicyAlgorithm": "HmacSHA1",
  "otpPolicyInitialCounter": 0,
  "otpPolicyDigits": 6,
  "otpPolicyLookAheadWindow": 1,
  "otpPolicyPeriod": 30,
  "otpSupportedApplications": [
    "FreeOTP",
    "Google Authenticator"
  ],
  "webAuthnPolicyRpEntityName": "keycloak",
  "webAuthnPolicySignatureAlgorithms": [
    "ES256"
  ],
  "webAuthnPolicyRpId": "",
  "webAuthnPolicyAttestationConveyancePreference": "not specified",
  "webAuthnPolicyAuthenticatorAttachment": "not specified",
  "webAuthnPolicyRequireResidentKey": "not specified",
  "webAuthnPolicyUserVerificationRequirement": "not specified",
  "webAuthnPolicyCreateTimeout": 0,
  "webAuthnPolicyAvoidSameAuthenticatorRegister": false,
  "webAuthnPolicyAcceptableAaguids": [],
  "webAuthnPolicyPasswordlessRpEntityName": "keycloak",
  "webAuthnPolicyPasswordlessSignatureAlgorithms": [
    "ES256"
  ],
  "webAuthnPolicyPasswordlessRpId": "",
  "webAuthnPolicyPasswordlessAttestationConveyancePreference": "not specified",
  "webAuthnPolicyPasswordlessAuthenticatorAttachment": "not specified",
  "webAuthnPolicyPasswordlessRequireResidentKey": "not specified",
  "webAuthnPolicyPasswordlessUserVerificationRequirement": "not specified",
  "webAuthnPolicyPasswordlessCreateTimeout": 0,
  "webAuthnPolicyPasswordlessAvoidSameAuthenticatorRegister": false,
  "webAuthnPolicyPasswordlessAcceptableAaguids": [],
  "scopeMappings": [
    {
      "clientScope": "offline_access",
      "roles": [
        "offline_access"
      ]
    }
  ],
  "clientScopeMappings": {
    "account": [
      {
        "client": "account-console",
        "roles": [
          "manage-account"
        ]
      }
    ]
  },
  "clients": [
    {
      "id": "566c3205-b080-462e-b430-c96cf518c781",
      "clientId": "account",
      "name": "${client_account}",
      "rootUrl": "${authBaseUrl}",
      "baseUrl": "/realms/rithysak/account/",
      "surrogateAuthRequired": false,
      "enabled": true,
      "alwaysDisplayInConsole": false,
      "clientAuthenticatorType": "client-secret",
      "redirectUris": [
        "/realms/rithysak/account/*"
      ],
      "webOrigins": [],
      "notBefore": 0,
      "bearerOnly": false,
      "consentRequired": false,
      "standardFlowEnabled": true,
      "implicitFlowEnabled": false,
      "directAccessGrantsEnabled": false,
      "serviceAccountsEnabled": false,
      "publicClient": true,
      "frontchannelLogout": false,
      "protocol": "openid-connect",
      "attributes": {},
      "authenticationFlowBindingOverrides": {},
      "fullScopeAllowed": false,
      "nodeReRegistrationTimeout": 0,
      "defaultClientScopes": [
        "web-origins",
        "roles",
        "profile",
        "email"
      ],
      "optionalClientScopes": [
        "address",
        "phone",
        "offline_access",
        "microprofile-jwt"
      ]
    },
    {
      "id": "5acdab94-e0b5-4383-a17d-d8df7c6df25b",
      "clientId": "account-console",
      "name": "${client_account-console}",
      "rootUrl": "${authBaseUrl}",
      "baseUrl": "/realms/rithysak/account/",
      "surrogateAuthRequired": false,
      "enabled": true,
      "alwaysDisplayInConsole": false,
      "clientAuthenticatorType": "client-secret",
      "redirectUris": [
        "/realms/rithysak/account/*"
      ],
      "webOrigins": [],
      "notBefore": 0,
      "bearerOnly": false,
      "consentRequired": false,
      "standardFlowEnabled": true,
      "implicitFlowEnabled": false,
      "directAccessGrantsEnabled": false,
      "serviceAccountsEnabled": false,
      "publicClient": true,
      "frontchannelLogout": false,
      "protocol": "openid-connect",
      "attributes": {
        "pkce.code.challenge.method": "S256"
      },
      "authenticationFlowBindingOverrides": {},
      "fullScopeAllowed": false,
      "nodeReRegistrationTimeout": 0,
      "protocolMappers": [
        {
          "id": "6374f04c-d1e0-4070-a957-e6200fbec68c",
          "name": "audience resolve",
          "protocol": "openid-connect",
          "protocolMapper": "oidc-audience-resolve-mapper",
          "consentRequired": false,
          "config": {}
        }
      ],
      "defaultClientScopes": [
        "web-origins",
        "roles",
        "profile",
        "email"
      ],
      "optionalClientScopes": [
        "address",
        "phone",
        "offline_access",
        "microprofile-jwt"
      ]
    },
    {
      "id": "f121e831-b1af-4367-8459-30d694ca6dcd",
      "clientId": "admin-cli",
      "name": "${client_admin-cli}",
      "surrogateAuthRequired": false,
      "enabled": true,
      "alwaysDisplayInConsole": false,
      "clientAuthenticatorType": "client-secret",
      "redirectUris": [],
      "webOrigins": [],
      "notBefore": 0,
      "bearerOnly": false,
      "consentRequired": false,
      "standardFlowEnabled": false,
      "implicitFlowEnabled": false,
      "directAccessGrantsEnabled": true,
      "serviceAccountsEnabled": false,
      "publicClient": true,
      "frontchannelLogout": false,
      "protocol": "openid-connect",
      "attributes": {},
      "authenticationFlowBindingOverrides": {},
      "fullScopeAllowed": false,
      "nodeReRegistrationTimeout": 0,
      "defaultClientScopes": [
        "web-origins",
        "roles",
        "profile",
        "email"
      ],
      "optionalClientScopes": [
        "address",
        "phone",
        "offline_access",
        "microprofile-jwt"
      ]
    },
    {
      "id": "c3568581-b28b-445d-b3b0-197b5d11a4f5",
      "clientId": "broker",
      "name": "${client_broker}",
      "surrogateAuthRequired": false,
      "enabled": true,
      "alwaysDisplayInConsole": false,
      "clientAuthenticatorType": "client-secret",
      "redirectUris": [],
      "webOrigins": [],
      "notBefore": 0,
      "bearerOnly": true,
      "consentRequired": false,
      "standardFlowEnabled": true,
      "implicitFlowEnabled": false,
      "directAccessGrantsEnabled": false,
      "serviceAccountsEnabled": false,
      "publicClient": false,
      "frontchannelLogout": false,
      "protocol": "openid-connect",
      "attributes": {},
      "authenticationFlowBindingOverrides": {},
      "fullScopeAllowed": false,
      "nodeReRegistrationTimeout": 0,
      "defaultClientScopes": [
        "web-origins",
        "roles",
        "profile",
        "email"
      ],
      "optionalClientScopes": [
        "address",
        "phone",
        "offline_access",
        "microprofile-jwt"
      ]
    },
    {
      "id": "841a68af-d514-4e41-be8e-d1dfeae9285e",
      "clientId": "realm-management",
      "name": "${client_realm-management}",
      "surrogateAuthRequired": false,
      "enabled": true,
      "alwaysDisplayInConsole": false,
      "clientAuthenticatorType": "client-secret",
      "redirectUris": [],
      "webOrigins": [],
      "notBefore": 0,
      "bearerOnly": true,
      "consentRequired": false,
      "standardFlowEnabled": true,
      "implicitFlowEnabled": false,
      "directAccessGrantsEnabled": false,
      "serviceAccountsEnabled": false,
      "publicClient": false,
      "frontchannelLogout": false,
      "protocol": "openid-connect",
      "attributes": {},
      "authenticationFlowBindingOverrides": {},
      "fullScopeAllowed": false,
      "nodeReRegistrationTimeout": 0,
      "defaultClientScopes": [
        "web-origins",
        "roles",
        "profile",
        "email"
      ],
      "optionalClientScopes": [
        "address",
        "phone",
        "offline_access",
        "microprofile-jwt"
      ]
    },
    {
      "id": "c6fbf53e-20a9-4226-91e1-27cfbfe00ae6",
      "clientId": "rithysak-client",
      "surrogateAuthRequired": false,
      "enabled": true,
      "alwaysDisplayInConsole": false,
      "clientAuthenticatorType": "client-secret",
      "secret": "**********",
      "redirectUris": [
        "http://localhost:8089/*"
      ],
      "webOrigins": [],
      "notBefore": 0,
      "bearerOnly": false,
      "consentRequired": false,
      "standardFlowEnabled": true,
      "implicitFlowEnabled": false,
      "directAccessGrantsEnabled": true,
      "serviceAccountsEnabled": false,
      "publicClient": false,
      "frontchannelLogout": false,
      "protocol": "openid-connect",
      "attributes": {
        "id.token.as.detached.signature": "false",
        "saml.assertion.signature": "false",
        "saml.force.post.binding": "false",
        "saml.multivalued.roles": "false",
        "saml.encrypt": "false",
        "oauth2.device.authorization.grant.enabled": "false",
        "backchannel.logout.revoke.offline.tokens": "false",
        "saml.server.signature": "false",
        "saml.server.signature.keyinfo.ext": "false",
        "use.refresh.tokens": "true",
        "exclude.session.state.from.auth.response": "false",
        "oidc.ciba.grant.enabled": "false",
        "saml.artifact.binding": "false",
        "backchannel.logout.session.required": "true",
        "client_credentials.use_refresh_token": "false",
        "saml_force_name_id_format": "false",
        "require.pushed.authorization.requests": "false",
        "saml.client.signature": "false",
        "tls.client.certificate.bound.access.tokens": "false",
        "saml.authnstatement": "false",
        "display.on.consent.screen": "false",
        "saml.onetimeuse.condition": "false"
      },
      "authenticationFlowBindingOverrides": {},
      "fullScopeAllowed": true,
      "nodeReRegistrationTimeout": -1,
      "defaultClientScopes": [
        "web-origins",
        "roles",
        "profile",
        "email"
      ],
      "optionalClientScopes": [
        "address",
        "phone",
        "offline_access",
        "microprofile-jwt"
      ]
    },
    {
      "id": "becf92f6-8fe3-4cc1-9284-05b8101e111b",
      "clientId": "security-admin-console",
      "name": "${client_security-admin-console}",
      "rootUrl": "${authAdminUrl}",
      "baseUrl": "/admin/rithysak/console/",
      "surrogateAuthRequired": false,
      "enabled": true,
      "alwaysDisplayInConsole": false,
      "clientAuthenticatorType": "client-secret",
      "redirectUris": [
        "/admin/rithysak/console/*"
      ],
      "webOrigins": [
        "+"
      ],
      "notBefore": 0,
      "bearerOnly": false,
      "consentRequired": false,
      "standardFlowEnabled": true,
      "implicitFlowEnabled": false,
      "directAccessGrantsEnabled": false,
      "serviceAccountsEnabled": false,
      "publicClient": true,
      "frontchannelLogout": false,
      "protocol": "openid-connect",
      "attributes": {
        "pkce.code.challenge.method": "S256"
      },
      "authenticationFlowBindingOverrides": {},
      "fullScopeAllowed": false,
      "nodeReRegistrationTimeout": 0,
      "protocolMappers": [
        {
          "id": "e811b79e-b8dc-4a27-aa33-760f1c117ab0",
          "name": "locale",
          "protocol": "openid-connect",
          "protocolMapper": "oidc-usermodel-attribute-mapper",
          "consentRequired": false,
          "config": {
            "userinfo.token.claim": "true",
            "user.attribute": "locale",
            "id.token.claim": "true",
            "access.token.claim": "true",
            "claim.name": "locale",
            "jsonType.label": "String"
          }
        }
      ],
      "defaultClientScopes": [
        "web-origins",
        "roles",
        "profile",
        "email"
      ],
      "optionalClientScopes": [
        "address",
        "phone",
        "offline_access",
        "microprofile-jwt"
      ]
    }
  ],
  "clientScopes": [
    {
      "id": "39d9bad8-1cd7-49e7-bea4-8bd414f2d3e9",
      "name": "microprofile-jwt",
      "description": "Microprofile - JWT built-in scope",
      "protocol": "openid-connect",
      "attributes": {
        "include.in.token.scope": "true",
        "display.on.consent.screen": "false"
      },
      "protocolMappers": [
        {
          "id": "cee00efa-f7d8-43c2-a86b-dc2b93d5dc22",
          "name": "upn",
          "protocol": "openid-connect",
          "protocolMapper": "oidc-usermodel-property-mapper",
          "consentRequired": false,
          "config": {
            "userinfo.token.claim": "true",
            "user.attribute": "username",
            "id.token.claim": "true",
            "access.token.claim": "true",
            "claim.name": "upn",
            "jsonType.label": "String"
          }
        },
        {
          "id": "afdda6aa-5c5e-42d3-a953-994c327ea282",
          "name": "groups",
          "protocol": "openid-connect",
          "protocolMapper": "oidc-usermodel-realm-role-mapper",
          "consentRequired": false,
          "config": {
            "multivalued": "true",
            "user.attribute": "foo",
            "id.token.claim": "true",
            "access.token.claim": "true",
            "claim.name": "groups",
            "jsonType.label": "String"
          }
        }
      ]
    },
    {
      "id": "940d3918-5cc0-4dd8-8eac-54bd9a79d5c3",
      "name": "role_list",
      "description": "SAML role list",
      "protocol": "saml",
      "attributes": {
        "consent.screen.text": "${samlRoleListScopeConsentText}",
        "display.on.consent.screen": "true"
      },
      "protocolMappers": [
        {
          "id": "40f1ede3-01c9-487a-b11c-7fc39611d03b",
          "name": "role list",
          "protocol": "saml",
          "protocolMapper": "saml-role-list-mapper",
          "consentRequired": false,
          "config": {
            "single": "false",
            "attribute.nameformat": "Basic",
            "attribute.name": "Role"
          }
        }
      ]
    },
    {
      "id": "b50e6d12-3cd6-406e-8532-b8e9343acead",
      "name": "address",
      "description": "OpenID Connect built-in scope: address",
      "protocol": "openid-connect",
      "attributes": {
        "include.in.token.scope": "true",
        "display.on.consent.screen": "true",
        "consent.screen.text": "${addressScopeConsentText}"
      },
      "protocolMappers": [
        {
          "id": "6d0ed904-43bf-476d-a3c4-c8a623a42dd1",
          "name": "address",
          "protocol": "openid-connect",
          "protocolMapper": "oidc-address-mapper",
          "consentRequired": false,
          "config": {
            "user.attribute.formatted": "formatted",
            "user.attribute.country": "country",
            "user.attribute.postal_code": "postal_code",
            "userinfo.token.claim": "true",
            "user.attribute.street": "street",
            "id.token.claim": "true",
            "user.attribute.region": "region",
            "access.token.claim": "true",
            "user.attribute.locality": "locality"
          }
        }
      ]
    },
    {
      "id": "3015bfc9-546e-4786-9d91-ef0ab1f185b4",
      "name": "email",
      "description": "OpenID Connect built-in scope: email",
      "protocol": "openid-connect",
      "attributes": {
        "include.in.token.scope": "true",
        "display.on.consent.screen": "true",
        "consent.screen.text": "${emailScopeConsentText}"
      },
      "protocolMappers": [
        {
          "id": "70597094-0508-43f4-ac85-8a4442a75d40",
          "name": "email verified",
          "protocol": "openid-connect",
          "protocolMapper": "oidc-usermodel-property-mapper",
          "consentRequired": false,
          "config": {
            "userinfo.token.claim": "true",
            "user.attribute": "emailVerified",
            "id.token.claim": "true",
            "access.token.claim": "true",
            "claim.name": "email_verified",
            "jsonType.label": "boolean"
          }
        },
        {
          "id": "1358c130-74ff-4b48-9ed9-583567652a9f",
          "name": "email",
          "protocol": "openid-connect",
          "protocolMapper": "oidc-usermodel-property-mapper",
          "consentRequired": false,
          "config": {
            "userinfo.token.claim": "true",
            "user.attribute": "email",
            "id.token.claim": "true",
            "access.token.claim": "true",
            "claim.name": "email",
            "jsonType.label": "String"
          }
        }
      ]
    },
    {
      "id": "d2017f32-8896-4b26-be60-23cfed74d003",
      "name": "roles",
      "description": "OpenID Connect scope for add user roles to the access token",
      "protocol": "openid-connect",
      "attributes": {
        "include.in.token.scope": "false",
        "display.on.consent.screen": "true",
        "consent.screen.text": "${rolesScopeConsentText}"
      },
      "protocolMappers": [
        {
          "id": "5e26e2da-a661-409c-a507-0f5d398d96e1",
          "name": "realm roles",
          "protocol": "openid-connect",
          "protocolMapper": "oidc-usermodel-realm-role-mapper",
          "consentRequired": false,
          "config": {
            "user.attribute": "foo",
            "access.token.claim": "true",
            "claim.name": "realm_access.roles",
            "jsonType.label": "String",
            "multivalued": "true"
          }
        },
        {
          "id": "599ae626-8b98-4f69-b2a7-40b34d149ca7",
          "name": "client roles",
          "protocol": "openid-connect",
          "protocolMapper": "oidc-usermodel-client-role-mapper",
          "consentRequired": false,
          "config": {
            "user.attribute": "foo",
            "access.token.claim": "true",
            "claim.name": "resource_access.${client_id}.roles",
            "jsonType.label": "String",
            "multivalued": "true"
          }
        },
        {
          "id": "e6abce92-bdf9-4785-8c86-a164d65ad4cb",
          "name": "audience resolve",
          "protocol": "openid-connect",
          "protocolMapper": "oidc-audience-resolve-mapper",
          "consentRequired": false,
          "config": {}
        }
      ]
    },
    {
      "id": "c068fd20-dd16-4f53-aafc-e7b70e603cb3",
      "name": "profile",
      "description": "OpenID Connect built-in scope: profile",
      "protocol": "openid-connect",
      "attributes": {
        "include.in.token.scope": "true",
        "display.on.consent.screen": "true",
        "consent.screen.text": "${profileScopeConsentText}"
      },
      "protocolMappers": [
        {
          "id": "f69f4111-e115-4a1c-aed7-4afe0f29c480",
          "name": "picture",
          "protocol": "openid-connect",
          "protocolMapper": "oidc-usermodel-attribute-mapper",
          "consentRequired": false,
          "config": {
            "userinfo.token.claim": "true",
            "user.attribute": "picture",
            "id.token.claim": "true",
            "access.token.claim": "true",
            "claim.name": "picture",
            "jsonType.label": "String"
          }
        },
        {
          "id": "5351805f-1fe6-4baf-8f72-13bc1985a482",
          "name": "birthdate",
          "protocol": "openid-connect",
          "protocolMapper": "oidc-usermodel-attribute-mapper",
          "consentRequired": false,
          "config": {
            "userinfo.token.claim": "true",
            "user.attribute": "birthdate",
            "id.token.claim": "true",
            "access.token.claim": "true",
            "claim.name": "birthdate",
            "jsonType.label": "String"
          }
        },
        {
          "id": "dcdc6b04-1c01-430b-bdb9-13af82d0ca60",
          "name": "updated at",
          "protocol": "openid-connect",
          "protocolMapper": "oidc-usermodel-attribute-mapper",
          "consentRequired": false,
          "config": {
            "userinfo.token.claim": "true",
            "user.attribute": "updatedAt",
            "id.token.claim": "true",
            "access.token.claim": "true",
            "claim.name": "updated_at",
            "jsonType.label": "String"
          }
        },
        {
          "id": "92138683-e38e-4e3f-93dd-b4d9fd623788",
          "name": "profile",
          "protocol": "openid-connect",
          "protocolMapper": "oidc-usermodel-attribute-mapper",
          "consentRequired": false,
          "config": {
            "userinfo.token.claim": "true",
            "user.attribute": "profile",
            "id.token.claim": "true",
            "access.token.claim": "true",
            "claim.name": "profile",
            "jsonType.label": "String"
          }
        },
        {
          "id": "bc744bc8-f156-4231-87a9-eb5cc9120055",
          "name": "zoneinfo",
          "protocol": "openid-connect",
          "protocolMapper": "oidc-usermodel-attribute-mapper",
          "consentRequired": false,
          "config": {
            "userinfo.token.claim": "true",
            "user.attribute": "zoneinfo",
            "id.token.claim": "true",
            "access.token.claim": "true",
            "claim.name": "zoneinfo",
            "jsonType.label": "String"
          }
        },
        {
          "id": "fd82b731-62b3-4759-8721-67f5f03aacc1",
          "name": "family name",
          "protocol": "openid-connect",
          "protocolMapper": "oidc-usermodel-property-mapper",
          "consentRequired": false,
          "config": {
            "userinfo.token.claim": "true",
            "user.attribute": "lastName",
            "id.token.claim": "true",
            "access.token.claim": "true",
            "claim.name": "family_name",
            "jsonType.label": "String"
          }
        },
        {
          "id": "fcd874c1-41e4-4012-a9ce-00aaf737cd72",
          "name": "username",
          "protocol": "openid-connect",
          "protocolMapper": "oidc-usermodel-property-mapper",
          "consentRequired": false,
          "config": {
            "userinfo.token.claim": "true",
            "user.attribute": "username",
            "id.token.claim": "true",
            "access.token.claim": "true",
            "claim.name": "preferred_username",
            "jsonType.label": "String"
          }
        },
        {
          "id": "dba06995-37de-41d1-99f7-a5fbfb543923",
          "name": "locale",
          "protocol": "openid-connect",
          "protocolMapper": "oidc-usermodel-attribute-mapper",
          "consentRequired": false,
          "config": {
            "userinfo.token.claim": "true",
            "user.attribute": "locale",
            "id.token.claim": "true",
            "access.token.claim": "true",
            "claim.name": "locale",
            "jsonType.label": "String"
          }
        },
        {
          "id": "56b75916-cbb1-4f0a-953b-084171a1afe3",
          "name": "gender",
          "protocol": "openid-connect",
          "protocolMapper": "oidc-usermodel-attribute-mapper",
          "consentRequired": false,
          "config": {
            "userinfo.token.claim": "true",
            "user.attribute": "gender",
            "id.token.claim": "true",
            "access.token.claim": "true",
            "claim.name": "gender",
            "jsonType.label": "String"
          }
        },
        {
          "id": "047bbbde-321b-463c-9691-b82cd74814cb",
          "name": "middle name",
          "protocol": "openid-connect",
          "protocolMapper": "oidc-usermodel-attribute-mapper",
          "consentRequired": false,
          "config": {
            "userinfo.token.claim": "true",
            "user.attribute": "middleName",
            "id.token.claim": "true",
            "access.token.claim": "true",
            "claim.name": "middle_name",
            "jsonType.label": "String"
          }
        },
        {
          "id": "b6b8a052-093d-44b5-9674-abd71dccece6",
          "name": "given name",
          "protocol": "openid-connect",
          "protocolMapper": "oidc-usermodel-property-mapper",
          "consentRequired": false,
          "config": {
            "userinfo.token.claim": "true",
            "user.attribute": "firstName",
            "id.token.claim": "true",
            "access.token.claim": "true",
            "claim.name": "given_name",
            "jsonType.label": "String"
          }
        },
        {
          "id": "323baaff-44b1-424f-8d75-2b749320e2dd",
          "name": "full name",
          "protocol": "openid-connect",
          "protocolMapper": "oidc-full-name-mapper",
          "consentRequired": false,
          "config": {
            "id.token.claim": "true",
            "access.token.claim": "true",
            "userinfo.token.claim": "true"
          }
        },
        {
          "id": "edb596b4-a616-4f81-b04e-88522e2dbc8d",
          "name": "website",
          "protocol": "openid-connect",
          "protocolMapper": "oidc-usermodel-attribute-mapper",
          "consentRequired": false,
          "config": {
            "userinfo.token.claim": "true",
            "user.attribute": "website",
            "id.token.claim": "true",
            "access.token.claim": "true",
            "claim.name": "website",
            "jsonType.label": "String"
          }
        },
        {
          "id": "2dad4669-4d32-491e-901a-7d5d5848312b",
          "name": "nickname",
          "protocol": "openid-connect",
          "protocolMapper": "oidc-usermodel-attribute-mapper",
          "consentRequired": false,
          "config": {
            "userinfo.token.claim": "true",
            "user.attribute": "nickname",
            "id.token.claim": "true",
            "access.token.claim": "true",
            "claim.name": "nickname",
            "jsonType.label": "String"
          }
        }
      ]
    },
    {
      "id": "0555e86b-2ddb-4872-b652-aa6b5d421e82",
      "name": "phone",
      "description": "OpenID Connect built-in scope: phone",
      "protocol": "openid-connect",
      "attributes": {
        "include.in.token.scope": "true",
        "display.on.consent.screen": "true",
        "consent.screen.text": "${phoneScopeConsentText}"
      },
      "protocolMappers": [
        {
          "id": "f915ada5-fd1b-41ea-94d1-78277f1f6504",
          "name": "phone number verified",
          "protocol": "openid-connect",
          "protocolMapper": "oidc-usermodel-attribute-mapper",
          "consentRequired": false,
          "config": {
            "userinfo.token.claim": "true",
            "user.attribute": "phoneNumberVerified",
            "id.token.claim": "true",
            "access.token.claim": "true",
            "claim.name": "phone_number_verified",
            "jsonType.label": "boolean"
          }
        },
        {
          "id": "117d95eb-31c6-4eaa-bfbb-111b03175cdc",
          "name": "phone number",
          "protocol": "openid-connect",
          "protocolMapper": "oidc-usermodel-attribute-mapper",
          "consentRequired": false,
          "config": {
            "userinfo.token.claim": "true",
            "user.attribute": "phoneNumber",
            "id.token.claim": "true",
            "access.token.claim": "true",
            "claim.name": "phone_number",
            "jsonType.label": "String"
          }
        }
      ]
    },
    {
      "id": "cf578da6-4d48-4004-b4e5-403cda5ea028",
      "name": "web-origins",
      "description": "OpenID Connect scope for add allowed web origins to the access token",
      "protocol": "openid-connect",
      "attributes": {
        "include.in.token.scope": "false",
        "display.on.consent.screen": "false",
        "consent.screen.text": ""
      },
      "protocolMappers": [
        {
          "id": "937adacf-81e1-4a04-9320-819fe07cb338",
          "name": "allowed web origins",
          "protocol": "openid-connect",
          "protocolMapper": "oidc-allowed-origins-mapper",
          "consentRequired": false,
          "config": {}
        }
      ]
    },
    {
      "id": "0121feb6-85d8-4cbb-853e-a7c84fe57efb",
      "name": "offline_access",
      "description": "OpenID Connect built-in scope: offline_access",
      "protocol": "openid-connect",
      "attributes": {
        "consent.screen.text": "${offlineAccessScopeConsentText}",
        "display.on.consent.screen": "true"
      }
    }
  ],
  "defaultDefaultClientScopes": [
    "role_list",
    "profile",
    "email",
    "roles",
    "web-origins"
  ],
  "defaultOptionalClientScopes": [
    "offline_access",
    "address",
    "phone",
    "microprofile-jwt"
  ],
  "browserSecurityHeaders": {
    "contentSecurityPolicyReportOnly": "",
    "xContentTypeOptions": "nosniff",
    "xRobotsTag": "none",
    "xFrameOptions": "SAMEORIGIN",
    "contentSecurityPolicy": "frame-src 'self'; frame-ancestors 'self'; object-src 'none';",
    "xXSSProtection": "1; mode=block",
    "strictTransportSecurity": "max-age=31536000; includeSubDomains"
  },
  "smtpServer": {},
  "eventsEnabled": false,
  "eventsListeners": [
    "jboss-logging"
  ],
  "enabledEventTypes": [],
  "adminEventsEnabled": false,
  "adminEventsDetailsEnabled": false,
  "identityProviders": [],
  "identityProviderMappers": [],
  "components": {
    "org.keycloak.services.clientregistration.policy.ClientRegistrationPolicy": [
      {
        "id": "71df40c7-ba10-43e9-bd33-1361aa99ddbd",
        "name": "Consent Required",
        "providerId": "consent-required",
        "subType": "anonymous",
        "subComponents": {},
        "config": {}
      },
      {
        "id": "a1c84eb4-016f-422b-9080-816baa2bc7e1",
        "name": "Allowed Client Scopes",
        "providerId": "allowed-client-templates",
        "subType": "anonymous",
        "subComponents": {},
        "config": {
          "allow-default-scopes": [
            "true"
          ]
        }
      },
      {
        "id": "3da0d4af-aaf5-4e5e-8fee-e6dc2720477d",
        "name": "Full Scope Disabled",
        "providerId": "scope",
        "subType": "anonymous",
        "subComponents": {},
        "config": {}
      },
      {
        "id": "e761e90d-55f9-4ed2-b779-2a33374ddc49",
        "name": "Max Clients Limit",
        "providerId": "max-clients",
        "subType": "anonymous",
        "subComponents": {},
        "config": {
          "max-clients": [
            "200"
          ]
        }
      },
      {
        "id": "9cafb9ea-bc54-40da-b82c-668ddbd3105b",
        "name": "Trusted Hosts",
        "providerId": "trusted-hosts",
        "subType": "anonymous",
        "subComponents": {},
        "config": {
          "host-sending-registration-request-must-match": [
            "true"
          ],
          "client-uris-must-match": [
            "true"
          ]
        }
      },
      {
        "id": "5c61f6e8-2e5a-4a63-a2f3-5f4cd992cade",
        "name": "Allowed Protocol Mapper Types",
        "providerId": "allowed-protocol-mappers",
        "subType": "anonymous",
        "subComponents": {},
        "config": {
          "allowed-protocol-mapper-types": [
            "saml-user-attribute-mapper",
            "oidc-usermodel-attribute-mapper",
            "oidc-full-name-mapper",
            "oidc-usermodel-property-mapper",
            "oidc-address-mapper",
            "saml-role-list-mapper",
            "saml-user-property-mapper",
            "oidc-sha256-pairwise-sub-mapper"
          ]
        }
      },
      {
        "id": "0756aba2-745d-42a8-97ca-2cc8499b82d8",
        "name": "Allowed Protocol Mapper Types",
        "providerId": "allowed-protocol-mappers",
        "subType": "authenticated",
        "subComponents": {},
        "config": {
          "allowed-protocol-mapper-types": [
            "oidc-usermodel-attribute-mapper",
            "saml-user-attribute-mapper",
            "oidc-usermodel-property-mapper",
            "oidc-address-mapper",
            "saml-user-property-mapper",
            "saml-role-list-mapper",
            "oidc-sha256-pairwise-sub-mapper",
            "oidc-full-name-mapper"
          ]
        }
      },
      {
        "id": "cf4d70b0-3da9-4c41-a4b0-a1d54447c26c",
        "name": "Allowed Client Scopes",
        "providerId": "allowed-client-templates",
        "subType": "authenticated",
        "subComponents": {},
        "config": {
          "allow-default-scopes": [
            "true"
          ]
        }
      }
    ],
    "org.keycloak.keys.KeyProvider": [
      {
        "id": "e651bdad-d8bd-41b9-aff0-964fd277f565",
        "name": "rsa-enc-generated",
        "providerId": "rsa-enc-generated",
        "subComponents": {},
        "config": {
          "priority": [
            "100"
          ],
          "algorithm": [
            "RSA-OAEP"
          ]
        }
      },
      {
        "id": "ad54bab4-3d56-46c5-9c67-d39ba2c7bccc",
        "name": "aes-generated",
        "providerId": "aes-generated",
        "subComponents": {},
        "config": {
          "priority": [
            "100"
          ]
        }
      },
      {
        "id": "0c509e70-9b04-4bdd-b047-7a6fc5edca3c",
        "name": "hmac-generated",
        "providerId": "hmac-generated",
        "subComponents": {},
        "config": {
          "priority": [
            "100"
          ],
          "algorithm": [
            "HS256"
          ]
        }
      },
      {
        "id": "3427f794-2898-4706-8afd-ec6cd2a3e199",
        "name": "rsa-generated",
        "providerId": "rsa-generated",
        "subComponents": {},
        "config": {
          "priority": [
            "100"
          ]
        }
      }
    ]
  },
  "internationalizationEnabled": false,
  "supportedLocales": [],
  "authenticationFlows": [
    {
      "id": "20150cbf-2976-4473-8921-06ddddd28004",
      "alias": "Account verification options",
      "description": "Method with which to verity the existing account",
      "providerId": "basic-flow",
      "topLevel": false,
      "builtIn": true,
      "authenticationExecutions": [
        {
          "authenticator": "idp-email-verification",
          "authenticatorFlow": false,
          "requirement": "ALTERNATIVE",
          "priority": 10,
          "userSetupAllowed": false,
          "autheticatorFlow": false
        },
        {
          "authenticatorFlow": true,
          "requirement": "ALTERNATIVE",
          "priority": 20,
          "flowAlias": "Verify Existing Account by Re-authentication",
          "userSetupAllowed": false,
          "autheticatorFlow": true
        }
      ]
    },
    {
      "id": "cf4528d2-f59e-476d-aba6-961a94e92654",
      "alias": "Authentication Options",
      "description": "Authentication options.",
      "providerId": "basic-flow",
      "topLevel": false,
      "builtIn": true,
      "authenticationExecutions": [
        {
          "authenticator": "basic-auth",
          "authenticatorFlow": false,
          "requirement": "REQUIRED",
          "priority": 10,
          "userSetupAllowed": false,
          "autheticatorFlow": false
        },
        {
          "authenticator": "basic-auth-otp",
          "authenticatorFlow": false,
          "requirement": "DISABLED",
          "priority": 20,
          "userSetupAllowed": false,
          "autheticatorFlow": false
        },
        {
          "authenticator": "auth-spnego",
          "authenticatorFlow": false,
          "requirement": "DISABLED",
          "priority": 30,
          "userSetupAllowed": false,
          "autheticatorFlow": false
        }
      ]
    },
    {
      "id": "32ba36e2-df92-4adc-a53f-7abe9fcf22b9",
      "alias": "Browser - Conditional OTP",
      "description": "Flow to determine if the OTP is required for the authentication",
      "providerId": "basic-flow",
      "topLevel": false,
      "builtIn": true,
      "authenticationExecutions": [
        {
          "authenticator": "conditional-user-configured",
          "authenticatorFlow": false,
          "requirement": "REQUIRED",
          "priority": 10,
          "userSetupAllowed": false,
          "autheticatorFlow": false
        },
        {
          "authenticator": "auth-otp-form",
          "authenticatorFlow": false,
          "requirement": "REQUIRED",
          "priority": 20,
          "userSetupAllowed": false,
          "autheticatorFlow": false
        }
      ]
    },
    {
      "id": "bb2c0bbc-9729-4e87-b7d8-dfe6f2f4b8d5",
      "alias": "Direct Grant - Conditional OTP",
      "description": "Flow to determine if the OTP is required for the authentication",
      "providerId": "basic-flow",
      "topLevel": false,
      "builtIn": true,
      "authenticationExecutions": [
        {
          "authenticator": "conditional-user-configured",
          "authenticatorFlow": false,
          "requirement": "REQUIRED",
          "priority": 10,
          "userSetupAllowed": false,
          "autheticatorFlow": false
        },
        {
          "authenticator": "direct-grant-validate-otp",
          "authenticatorFlow": false,
          "requirement": "REQUIRED",
          "priority": 20,
          "userSetupAllowed": false,
          "autheticatorFlow": false
        }
      ]
    },
    {
      "id": "5dd200a5-be97-440c-a873-e8038ece12e3",
      "alias": "First broker login - Conditional OTP",
      "description": "Flow to determine if the OTP is required for the authentication",
      "providerId": "basic-flow",
      "topLevel": false,
      "builtIn": true,
      "authenticationExecutions": [
        {
          "authenticator": "conditional-user-configured",
          "authenticatorFlow": false,
          "requirement": "REQUIRED",
          "priority": 10,
          "userSetupAllowed": false,
          "autheticatorFlow": false
        },
        {
          "authenticator": "auth-otp-form",
          "authenticatorFlow": false,
          "requirement": "REQUIRED",
          "priority": 20,
          "userSetupAllowed": false,
          "autheticatorFlow": false
        }
      ]
    },
    {
      "id": "d5ef1a34-6ab7-41c3-8002-23d73e1dd155",
      "alias": "Handle Existing Account",
      "description": "Handle what to do if there is existing account with same email/username like authenticated identity provider",
      "providerId": "basic-flow",
      "topLevel": false,
      "builtIn": true,
      "authenticationExecutions": [
        {
          "authenticator": "idp-confirm-link",
          "authenticatorFlow": false,
          "requirement": "REQUIRED",
          "priority": 10,
          "userSetupAllowed": false,
          "autheticatorFlow": false
        },
        {
          "authenticatorFlow": true,
          "requirement": "REQUIRED",
          "priority": 20,
          "flowAlias": "Account verification options",
          "userSetupAllowed": false,
          "autheticatorFlow": true
        }
      ]
    },
    {
      "id": "32204a8f-047a-40db-b48f-8a27b14c1583",
      "alias": "Reset - Conditional OTP",
      "description": "Flow to determine if the OTP should be reset or not. Set to REQUIRED to force.",
      "providerId": "basic-flow",
      "topLevel": false,
      "builtIn": true,
      "authenticationExecutions": [
        {
          "authenticator": "conditional-user-configured",
          "authenticatorFlow": false,
          "requirement": "REQUIRED",
          "priority": 10,
          "userSetupAllowed": false,
          "autheticatorFlow": false
        },
        {
          "authenticator": "reset-otp",
          "authenticatorFlow": false,
          "requirement": "REQUIRED",
          "priority": 20,
          "userSetupAllowed": false,
          "autheticatorFlow": false
        }
      ]
    },
    {
      "id": "f95d5db2-3ce7-423b-9e92-a0ae37446697",
      "alias": "User creation or linking",
      "description": "Flow for the existing/non-existing user alternatives",
      "providerId": "basic-flow",
      "topLevel": false,
      "builtIn": true,
      "authenticationExecutions": [
        {
          "authenticatorConfig": "create unique user config",
          "authenticator": "idp-create-user-if-unique",
          "authenticatorFlow": false,
          "requirement": "ALTERNATIVE",
          "priority": 10,
          "userSetupAllowed": false,
          "autheticatorFlow": false
        },
        {
          "authenticatorFlow": true,
          "requirement": "ALTERNATIVE",
          "priority": 20,
          "flowAlias": "Handle Existing Account",
          "userSetupAllowed": false,
          "autheticatorFlow": true
        }
      ]
    },
    {
      "id": "3a9001b3-d109-426e-899e-1f0bb31e92c1",
      "alias": "Verify Existing Account by Re-authentication",
      "description": "Reauthentication of existing account",
      "providerId": "basic-flow",
      "topLevel": false,
      "builtIn": true,
      "authenticationExecutions": [
        {
          "authenticator": "idp-username-password-form",
          "authenticatorFlow": false,
          "requirement": "REQUIRED",
          "priority": 10,
          "userSetupAllowed": false,
          "autheticatorFlow": false
        },
        {
          "authenticatorFlow": true,
          "requirement": "CONDITIONAL",
          "priority": 20,
          "flowAlias": "First broker login - Conditional OTP",
          "userSetupAllowed": false,
          "autheticatorFlow": true
        }
      ]
    },
    {
      "id": "bf7cf155-4b91-4f6d-9634-12d6e54cd046",
      "alias": "browser",
      "description": "browser based authentication",
      "providerId": "basic-flow",
      "topLevel": true,
      "builtIn": true,
      "authenticationExecutions": [
        {
          "authenticator": "auth-cookie",
          "authenticatorFlow": false,
          "requirement": "ALTERNATIVE",
          "priority": 10,
          "userSetupAllowed": false,
          "autheticatorFlow": false
        },
        {
          "authenticator": "auth-spnego",
          "authenticatorFlow": false,
          "requirement": "DISABLED",
          "priority": 20,
          "userSetupAllowed": false,
          "autheticatorFlow": false
        },
        {
          "authenticator": "identity-provider-redirector",
          "authenticatorFlow": false,
          "requirement": "ALTERNATIVE",
          "priority": 25,
          "userSetupAllowed": false,
          "autheticatorFlow": false
        },
        {
          "authenticatorFlow": true,
          "requirement": "ALTERNATIVE",
          "priority": 30,
          "flowAlias": "forms",
          "userSetupAllowed": false,
          "autheticatorFlow": true
        }
      ]
    },
    {
      "id": "fc595a86-a3ff-4bb6-85e3-cebd9ab018eb",
      "alias": "clients",
      "description": "Base authentication for clients",
      "providerId": "client-flow",
      "topLevel": true,
      "builtIn": true,
      "authenticationExecutions": [
        {
          "authenticator": "client-secret",
          "authenticatorFlow": false,
          "requirement": "ALTERNATIVE",
          "priority": 10,
          "userSetupAllowed": false,
          "autheticatorFlow": false
        },
        {
          "authenticator": "client-jwt",
          "authenticatorFlow": false,
          "requirement": "ALTERNATIVE",
          "priority": 20,
          "userSetupAllowed": false,
          "autheticatorFlow": false
        },
        {
          "authenticator": "client-secret-jwt",
          "authenticatorFlow": false,
          "requirement": "ALTERNATIVE",
          "priority": 30,
          "userSetupAllowed": false,
          "autheticatorFlow": false
        },
        {
          "authenticator": "client-x509",
          "authenticatorFlow": false,
          "requirement": "ALTERNATIVE",
          "priority": 40,
          "userSetupAllowed": false,
          "autheticatorFlow": false
        }
      ]
    },
    {
      "id": "5d62433f-52f8-4708-aaf2-d7ca3748d1d8",
      "alias": "direct grant",
      "description": "OpenID Connect Resource Owner Grant",
      "providerId": "basic-flow",
      "topLevel": true,
      "builtIn": true,
      "authenticationExecutions": [
        {
          "authenticator": "direct-grant-validate-username",
          "authenticatorFlow": false,
          "requirement": "REQUIRED",
          "priority": 10,
          "userSetupAllowed": false,
          "autheticatorFlow": false
        },
        {
          "authenticator": "direct-grant-validate-password",
          "authenticatorFlow": false,
          "requirement": "REQUIRED",
          "priority": 20,
          "userSetupAllowed": false,
          "autheticatorFlow": false
        },
        {
          "authenticatorFlow": true,
          "requirement": "CONDITIONAL",
          "priority": 30,
          "flowAlias": "Direct Grant - Conditional OTP",
          "userSetupAllowed": false,
          "autheticatorFlow": true
        }
      ]
    },
    {
      "id": "1121bd93-d055-4da7-b096-6ed50e58db50",
      "alias": "docker auth",
      "description": "Used by Docker clients to authenticate against the IDP",
      "providerId": "basic-flow",
      "topLevel": true,
      "builtIn": true,
      "authenticationExecutions": [
        {
          "authenticator": "docker-http-basic-authenticator",
          "authenticatorFlow": false,
          "requirement": "REQUIRED",
          "priority": 10,
          "userSetupAllowed": false,
          "autheticatorFlow": false
        }
      ]
    },
    {
      "id": "6c184c4c-9bd8-4e6b-8c79-bb66b3020f35",
      "alias": "first broker login",
      "description": "Actions taken after first broker login with identity provider account, which is not yet linked to any Keycloak account",
      "providerId": "basic-flow",
      "topLevel": true,
      "builtIn": true,
      "authenticationExecutions": [
        {
          "authenticatorConfig": "review profile config",
          "authenticator": "idp-review-profile",
          "authenticatorFlow": false,
          "requirement": "REQUIRED",
          "priority": 10,
          "userSetupAllowed": false,
          "autheticatorFlow": false
        },
        {
          "authenticatorFlow": true,
          "requirement": "REQUIRED",
          "priority": 20,
          "flowAlias": "User creation or linking",
          "userSetupAllowed": false,
          "autheticatorFlow": true
        }
      ]
    },
    {
      "id": "3713ec66-0b06-4879-880c-4da643036aea",
      "alias": "forms",
      "description": "Username, password, otp and other auth forms.",
      "providerId": "basic-flow",
      "topLevel": false,
      "builtIn": true,
      "authenticationExecutions": [
        {
          "authenticator": "auth-username-password-form",
          "authenticatorFlow": false,
          "requirement": "REQUIRED",
          "priority": 10,
          "userSetupAllowed": false,
          "autheticatorFlow": false
        },
        {
          "authenticatorFlow": true,
          "requirement": "CONDITIONAL",
          "priority": 20,
          "flowAlias": "Browser - Conditional OTP",
          "userSetupAllowed": false,
          "autheticatorFlow": true
        }
      ]
    },
    {
      "id": "14793eb5-e104-4412-aab3-612fb0449908",
      "alias": "http challenge",
      "description": "An authentication flow based on challenge-response HTTP Authentication Schemes",
      "providerId": "basic-flow",
      "topLevel": true,
      "builtIn": true,
      "authenticationExecutions": [
        {
          "authenticator": "no-cookie-redirect",
          "authenticatorFlow": false,
          "requirement": "REQUIRED",
          "priority": 10,
          "userSetupAllowed": false,
          "autheticatorFlow": false
        },
        {
          "authenticatorFlow": true,
          "requirement": "REQUIRED",
          "priority": 20,
          "flowAlias": "Authentication Options",
          "userSetupAllowed": false,
          "autheticatorFlow": true
        }
      ]
    },
    {
      "id": "129f28f4-a4f4-46cc-aa02-41e8f6e00bf5",
      "alias": "registration",
      "description": "registration flow",
      "providerId": "basic-flow",
      "topLevel": true,
      "builtIn": true,
      "authenticationExecutions": [
        {
          "authenticator": "registration-page-form",
          "authenticatorFlow": true,
          "requirement": "REQUIRED",
          "priority": 10,
          "flowAlias": "registration form",
          "userSetupAllowed": false,
          "autheticatorFlow": true
        }
      ]
    },
    {
      "id": "f405b600-e9b5-40cf-8d6c-28e412d35921",
      "alias": "registration form",
      "description": "registration form",
      "providerId": "form-flow",
      "topLevel": false,
      "builtIn": true,
      "authenticationExecutions": [
        {
          "authenticator": "registration-user-creation",
          "authenticatorFlow": false,
          "requirement": "REQUIRED",
          "priority": 20,
          "userSetupAllowed": false,
          "autheticatorFlow": false
        },
        {
          "authenticator": "registration-profile-action",
          "authenticatorFlow": false,
          "requirement": "REQUIRED",
          "priority": 40,
          "userSetupAllowed": false,
          "autheticatorFlow": false
        },
        {
          "authenticator": "registration-password-action",
          "authenticatorFlow": false,
          "requirement": "REQUIRED",
          "priority": 50,
          "userSetupAllowed": false,
          "autheticatorFlow": false
        },
        {
          "authenticator": "registration-recaptcha-action",
          "authenticatorFlow": false,
          "requirement": "DISABLED",
          "priority": 60,
          "userSetupAllowed": false,
          "autheticatorFlow": false
        }
      ]
    },
    {
      "id": "8b5c79fe-0eae-4c8f-9481-c8fd78cf7e9e",
      "alias": "reset credentials",
      "description": "Reset credentials for a user if they forgot their password or something",
      "providerId": "basic-flow",
      "topLevel": true,
      "builtIn": true,
      "authenticationExecutions": [
        {
          "authenticator": "reset-credentials-choose-user",
          "authenticatorFlow": false,
          "requirement": "REQUIRED",
          "priority": 10,
          "userSetupAllowed": false,
          "autheticatorFlow": false
        },
        {
          "authenticator": "reset-credential-email",
          "authenticatorFlow": false,
          "requirement": "REQUIRED",
          "priority": 20,
          "userSetupAllowed": false,
          "autheticatorFlow": false
        },
        {
          "authenticator": "reset-password",
          "authenticatorFlow": false,
          "requirement": "REQUIRED",
          "priority": 30,
          "userSetupAllowed": false,
          "autheticatorFlow": false
        },
        {
          "authenticatorFlow": true,
          "requirement": "CONDITIONAL",
          "priority": 40,
          "flowAlias": "Reset - Conditional OTP",
          "userSetupAllowed": false,
          "autheticatorFlow": true
        }
      ]
    },
    {
      "id": "3040d2e9-896f-46fc-a1be-ddf46864450c",
      "alias": "saml ecp",
      "description": "SAML ECP Profile Authentication Flow",
      "providerId": "basic-flow",
      "topLevel": true,
      "builtIn": true,
      "authenticationExecutions": [
        {
          "authenticator": "http-basic-authenticator",
          "authenticatorFlow": false,
          "requirement": "REQUIRED",
          "priority": 10,
          "userSetupAllowed": false,
          "autheticatorFlow": false
        }
      ]
    }
  ],
  "authenticatorConfig": [
    {
      "id": "ad185162-fbc1-4ff8-bd63-744a9aebcb79",
      "alias": "create unique user config",
      "config": {
        "require.password.update.after.registration": "false"
      }
    },
    {
      "id": "2d367c21-2684-4167-8c14-0e9dd4952fd0",
      "alias": "review profile config",
      "config": {
        "update.profile.on.first.login": "missing"
      }
    }
  ],
  "requiredActions": [
    {
      "alias": "CONFIGURE_TOTP",
      "name": "Configure OTP",
      "providerId": "CONFIGURE_TOTP",
      "enabled": true,
      "defaultAction": false,
      "priority": 10,
      "config": {}
    },
    {
      "alias": "terms_and_conditions",
      "name": "Terms and Conditions",
      "providerId": "terms_and_conditions",
      "enabled": false,
      "defaultAction": false,
      "priority": 20,
      "config": {}
    },
    {
      "alias": "UPDATE_PASSWORD",
      "name": "Update Password",
      "providerId": "UPDATE_PASSWORD",
      "enabled": true,
      "defaultAction": false,
      "priority": 30,
      "config": {}
    },
    {
      "alias": "UPDATE_PROFILE",
      "name": "Update Profile",
      "providerId": "UPDATE_PROFILE",
      "enabled": true,
      "defaultAction": false,
      "priority": 40,
      "config": {}
    },
    {
      "alias": "VERIFY_EMAIL",
      "name": "Verify Email",
      "providerId": "VERIFY_EMAIL",
      "enabled": true,
      "defaultAction": false,
      "priority": 50,
      "config": {}
    },
    {
      "alias": "delete_account",
      "name": "Delete Account",
      "providerId": "delete_account",
      "enabled": false,
      "defaultAction": false,
      "priority": 60,
      "config": {}
    },
    {
      "alias": "update_user_locale",
      "name": "Update User Locale",
      "providerId": "update_user_locale",
      "enabled": true,
      "defaultAction": false,
      "priority": 1000,
      "config": {}
    }
  ],
  "browserFlow": "browser",
  "registrationFlow": "registration",
  "directGrantFlow": "direct grant",
  "resetCredentialsFlow": "reset credentials",
  "clientAuthenticationFlow": "clients",
  "dockerAuthenticationFlow": "docker auth",
  "attributes": {
    "cibaBackchannelTokenDeliveryMode": "poll",
    "cibaExpiresIn": "120",
    "cibaAuthRequestedUserHint": "login_hint",
    "oauth2DeviceCodeLifespan": "600",
    "oauth2DevicePollingInterval": "5",
    "parRequestUriLifespan": "60",
    "cibaInterval": "5"
  },
  "keycloakVersion": "16.1.1",
  "userManagedAccessAllowed": false,
  "clientProfiles": {
    "profiles": []
  },
  "clientPolicies": {
    "policies": []
  }
}